timerpy/__init__.py
timerpy/timer.py
timerpy-1.1.0.dist-info/LICENSE
timerpy-1.1.0.dist-info/METADATA
timerpy-1.1.0.dist-info/WHEEL
timerpy-1.1.0.dist-info/top_level.txt
timerpy-1.1.0.dist-info/RECORD
